README.rst
setup.py
pybitflyer/__init__.py
pybitflyer/exception.py
pybitflyer/pybitflyer.py
pybitflyer.egg-info/PKG-INFO
pybitflyer.egg-info/SOURCES.txt
pybitflyer.egg-info/dependency_links.txt
pybitflyer.egg-info/pbr.json
pybitflyer.egg-info/requires.txt
pybitflyer.egg-info/top_level.txt